discordreactivev2
