Metadata-Version: 2.1
Name: discordreactivev2
Version: 0.3
Summary: Kunders Package
Home-page: https://github.com/0xe2d0/evil-pip
Download-URL: https://github.com/0xe2d0/evil-pip/tarball/master
Author: Kunder
License: MIT
